django_markov/__init__.py
django_markov/admin.py
django_markov/apps.py
django_markov/models.py
django_markov/py.typed
django_markov/text_models.py
django_markov/urls.py
django_markov/views.py
django_markov/migrations/0001_initial.py
django_markov/migrations/0002_alter_markovtextmodel_created_and_more.py
django_markov/migrations/0003_markovtextmodel_compiled.py
django_markov/migrations/0004_remove_markovtextmodel_compiled.py
django_markov/migrations/0005_alter_markovtextmodel_data.py
django_markov/migrations/__init__.py
django_markov-0.5.0.dist-info/METADATA
django_markov-0.5.0.dist-info/WHEEL
django_markov-0.5.0.dist-info/licenses/LICENSE
django_markov-0.5.0.dist-info/RECORD
