Metadata-Version: 2.4
Name: django-markov
Version: 0.5.0
Summary: django-markov is a reusable Django app that enables you to create Markov text models, and store them in the database. Those models can then be used to generate Markov chain sentences.
Project-URL: Repository, https://codeberg.org/andrlik/django-markov
Project-URL: Documentation, https://django-markov.readthedocs.io/en/latest/
Project-URL: Homepage, https://django-markov.readthedocs.io/en/latest/
Author-email: Daniel Andrlik <daniel@andrlik.org>
License-Expression: BSD-3-Clause
License-File: LICENSE
Classifier: Development Status :: 4 - Beta
Classifier: Framework :: Django
Classifier: Framework :: Django :: 5.1
Classifier: Framework :: Django :: 5.2
Classifier: License :: OSI Approved :: BSD License
Classifier: Programming Language :: Python :: 3.12
Classifier: Programming Language :: Python :: 3.13
Requires-Python: >=3.12
Requires-Dist: django>=5.1
Requires-Dist: markovify>=0.9.4
Requires-Dist: spacy>=3.8.7
Provides-Extra: test
Requires-Dist: argon2-cffi; extra == 'test'
Requires-Dist: django-coverage; extra == 'test'
Requires-Dist: django-coverage-plugin; extra == 'test'
Requires-Dist: django-environ; extra == 'test'
Requires-Dist: django-extensions; extra == 'test'
Requires-Dist: faker; extra == 'test'
Requires-Dist: pytest-asyncio; extra == 'test'
Requires-Dist: pytest-cov; extra == 'test'
Requires-Dist: pytest-django; extra == 'test'
Requires-Dist: pytest-mock; extra == 'test'
Requires-Dist: pytest-sugar; extra == 'test'
